streamlit_datacard/__init__.py
streamlit_datacard/example.py
streamlit_datacard/frontend/build/bootstrap.min.css
streamlit_datacard/frontend/build/index.html
streamlit_datacard/frontend/build/assets/index-_LSI08-C.js
streamlit_datacard-0.1.1.dist-info/licenses/LICENSE
streamlit_datacard-0.1.1.dist-info/METADATA
streamlit_datacard-0.1.1.dist-info/WHEEL
streamlit_datacard-0.1.1.dist-info/top_level.txt
streamlit_datacard-0.1.1.dist-info/RECORD
